{
  "id": "symantec.endpointprotection.14.3",
  "name": "Symantec Endpoint Protection 14.3",
  "version": "14.3",
  "publisher": "Symantec",
  "description": "Symantec Endpoint Protection 14.3 14.3 - enterprise packaging template.",
  "source": {
    "type": "local",
    "relativePath": "payload\\\\setup.exe"
  },
  "installer": {
    "type": "exe",
    "relativePath": "payload\\\\setup.exe",
    "silentArgs": "/quiet /norestart",
    "uninstallCmd": "UNKNOWN_SEP_UNINSTALL"
  },
  "detection": {
    "type": "uninstallReg",
    "keyPath": "HKLM\\\\SOFTWARE\\\\Microsoft\\\\Windows\\\\CurrentVersion\\\\Uninstall",
    "valueName": "DisplayName",
    "operator": "contains",
    "expectedValue": "Symantec Endpoint Protection 14.3"
  },
  "requirements": {
    "minOSVersion": "10.0.14393",
    "architecture": "x64"
  },
  "intuneHints": {
    "displayName": "Symantec Endpoint Protection 14.3 14.3",
    "category": "Security",
    "restartBehavior": "suppress",
    "notifications": "showAll"
  },
  "variables": {},
  "caveats": [
    "Coexistence with other AV products not recommended.",
    "May require migration from on-prem SEPM to cloud."
  ],
  "review": {
    "reviewed": false,
    "reviewedBy": null,
    "reviewedDate": null
  }
}